__init__.py
mqss/__init__.py
mqss/pennylane_adapter/__init__.py
mqss/pennylane_adapter/adapter.py
mqss/pennylane_adapter/backend.py
mqss/pennylane_adapter/config.py
mqss/pennylane_adapter/device.py
mqss/pennylane_adapter/job.py
mqss/pennylane_adapter/mqp_resources.py
mqss/pennylane_adapter/utils.py
pennylane_adapter-1.0.0.dist-info/METADATA
pennylane_adapter-1.0.0.dist-info/WHEEL
pennylane_adapter-1.0.0.dist-info/top_level.txt
pennylane_adapter-1.0.0.dist-info/RECORD
