Metadata-Version: 2.4
Name: pennylane-adapter
Version: 1.0.0
Summary: A Pennylane Adapter package for the Munich Quantum Software Stack.
Author-email: Burak <burak.mete@lrz.de>
Requires-Python: >=3.11
Requires-Dist: pennylane>=0.39.0
Requires-Dist: pytest>=8.3.3
Requires-Dist: python-dotenv>=1.0.1
Requires-Dist: qiskit>=1.2.4
Requires-Dist: requests>=2.32.3
Requires-Dist: mqp-client==0.1.4
